twgen/__init__.py
twgen/main.py
twgen-0.1.0.dist-info/METADATA
twgen-0.1.0.dist-info/WHEEL
twgen-0.1.0.dist-info/entry_points.txt
twgen-0.1.0.dist-info/RECORD
